ultttt/__init__.py
ultttt/__main__.pyw
ultttt/_pyinstaller_ultttt.pyw
ultttt/_tic_tac_toe.py
ultttt/_ultimate_tic_tac_toe.py
ultttt/icon.png
ultttt/py.typed
ultttt-1.0.0.dist-info/METADATA
ultttt-1.0.0.dist-info/WHEEL
ultttt-1.0.0.dist-info/entry_points.txt
ultttt-1.0.0.dist-info/licenses/LICENSE
ultttt-1.0.0.dist-info/RECORD
