Metadata-Version: 2.3
Name: ultttt
Version: 1.0.0
Summary: ♟️ Ultimate tic-tac-toe game GUI application using Python and PyGame
Project-URL: homepage, https://github.com/jcbhmr/ultttt
Project-URL: source, https://github.com/jcbhmr/ultttt.git
Project-URL: download, https://github.com/jcbhmr/ultttt/releases/latest
Author-email: Jacob Hummer <jcbhmr@outlook.com>
Keywords: board-game,gui,pygame,python,tic-tac-toe,ultimate-tic-tac-toe,uv
Classifier: Intended Audience :: Education
Classifier: License :: OSI Approved :: MIT License
Classifier: Programming Language :: Python :: 3.12
Classifier: Topic :: Games/Entertainment :: Board Games
Requires-Python: >=3.12
Requires-Dist: pygame>=2.6.1
